setup.py
trunity_migrator/__init__.py
trunity_migrator/fixers.py
trunity_migrator/glossary.py
trunity_migrator/html_fixer.py
trunity_migrator/migrator.py
trunity_migrator/settings.py
trunity_migrator/trunity_2_client.py
trunity_migrator.egg-info/PKG-INFO
trunity_migrator.egg-info/SOURCES.txt
trunity_migrator.egg-info/dependency_links.txt
trunity_migrator.egg-info/requires.txt
trunity_migrator.egg-info/top_level.txt
trunity_migrator/bin/__init__.py
trunity_migrator/bin/trunity-migrator
trunity_migrator/questionnaires/__init__.py
trunity_migrator/questionnaires/answer_converters.py
trunity_migrator/questionnaires/uploaders.py
trunity_migrator/questionnaires/tests/__init__.py
trunity_migrator/questionnaires/tests/test_answer_converters.py
trunity_migrator/self_assessments/__init__.py
trunity_migrator/self_assessments/answer_converters.py
trunity_migrator/self_assessments/uploaders.py
trunity_migrator/self_assessments/tests/__init__.py
trunity_migrator/self_assessments/tests/test_answer_converters.py
trunity_migrator/tests/__init__.py
trunity_migrator/tests/test_fixers.py
trunity_migrator/utils/__init__.py
trunity_migrator/utils/static.py
trunity_migrator/utils/tests/__init__.py
trunity_migrator/utils/tests/test_static.py
var/__init__.py
var/run_migrator.py
var/settings.py
var/test_client.py
var/warnings_test.py