Metadata-Version: 1.0
Name: trunity-migrator
Version: 0.5.4
Summary: Library for migrating content from Trunity 2 to Trunity 3 learning platform.
Home-page: UNKNOWN
Author: hunting
Author-email: VicHunting@yandex.ua
License: MIT
Platform: UNKNOWN
